{
    "name": "Nel Paradiso",
    "phone": "76967579",
    "email": null,
    "web": null,
    "est_type": "restaurant",
    "bus_type": "private",
    "cuisine": "others",
    "hours": {
        "open": "11:00",
        "close": "23:30",
        "days": [
            "mon",
            "tue",
            "wed",
            "thu",
            "fri",
            "sat",
            "sun"
        ]
    },
    "cap": null,
    "reservations": [
        "in-person"
    ],
    "delivery": [
        "home",
        "takeaway",
        "on-site"
    ],
    "level": "medium",
    "payment": [
        "cash",
        "transfer",
        "card"
    ],
    "promo": false,
    "rating": 4.5,
    "reviews": 75,
    "amenities": [
        "parking"
    ],
    "fb": "https://www.facebook.com/NELPARADISORESTAURANTE/",
    "ig": "@nelparadiso",
    "twitter": null,
    "menu": [
        {
            "name": "Croquetas de la casa con salsa rosa",
            "price": 792,
            "type": "appetizer"
        },
        {
            "name": "Frituras de la casa con miel y mostaza",
            "price": 880,
            "type": "appetizer"
        },
        {
            "name": "Bastones de Pollo con salsa rosa",
            "price": 1760,
            "type": "appetizer"
        },
        {
            "name": "Bastones de Mar en salsa alioli",
            "price": 1760,
            "type": "appetizer"
        },
        {
            "name": "Tamal en Cazuela",
            "price": 1584,
            "type": "appetizer"
        },
        {
            "name": "Tamal Marinero",
            "price": 2376,
            "type": "appetizer"
        },
        {
            "name": "Ensalada de Atún y Huevo",
            "price": 1760,
            "type": "appetizer"
        },
        {
            "name": "Ceviche de Pescado",
            "price": 1584,
            "type": "appetizer"
        },
        {
            "name": "Picadera Paraíso",
            "price": 2992,
            "type": "appetizer"
        },
        {
            "name": "Coctel de Camarones",
            "price": 1936,
            "type": "appetizer"
        },
        {
            "name": "Cóctel de Langosta",
            "price": 2112,
            "type": "appetizer"
        },
        {
            "name": "Tabla de Quesos",
            "price": 2816,
            "type": "appetizer"
        },
        {
            "name": "Lonjas de Jamón Serrano",
            "price": 2640,
            "type": "appetizer"
        },
        {
            "name": "Tabla Mixta de Quesos y Jamón Serrano",
            "price": 4048,
            "type": "appetizer"
        },
        {
            "name": "Salmón Paradiso",
            "price": 2816,
            "type": "appetizer"
        },
        {
            "name": "Bistec de CERDO glaseado al Vino Tinto",
            "price": 2112,
            "type": "mains"
        },
        {
            "name": "Chuleta en salsa Verde",
            "price": 2288,
            "type": "mains"
        },
        {
            "name": "Solomillo de Cerdo al estilo del Chef",
            "price": 2816,
            "type": "mains"
        },
        {
            "name": "Entrecot de Cerdo",
            "price": 3520,
            "type": "mains"
        },
        {
            "name": "Lomo Ahumado",
            "price": 2464,
            "type": "mains"
        },
        {
            "name": "Estofado de Cerdo",
            "price": 6600,
            "type": "mains"
        },
        {
            "name": "Ropa Vieja de Res",
            "price": 2552,
            "type": "mains"
        },
        {
            "name": "Bistec de Res",
            "price": 2904,
            "type": "mains"
        },
        {
            "name": "Fajita de Res",
            "price": 2464,
            "type": "mains"
        },
        {
            "name": "Filete a la Douche",
            "price": 2990,
            "type": "mains"
        },
        {
            "name": "Filete Mignon/Churrasco",
            "price": 3872,
            "type": "mains"
        },
        {
            "name": "Chateaubriand",
            "price": 5280,
            "type": "mains"
        },
        {
            "name": "Striploin",
            "price": 3872,
            "type": "mains"
        },
        {
            "name": "Ropa Vieja de Cordero",
            "price": 1848,
            "type": "mains"
        },
        {
            "name": "Cabrito Picoso",
            "price": 2640,
            "type": "mains"
        },
        {
            "name": "Cordero al Vino Tinto",
            "price": 2464,
            "type": "mains"
        },
        {
            "name": "Pechuga Grille",
            "price": 2112,
            "type": "mains"
        },
        {
            "name": "Jardinera de Pechuga",
            "price": 2464,
            "type": "mains"
        },
        {
            "name": "Pechuga Roquefort",
            "price": 2816,
            "type": "mains"
        },
        {
            "name": "Pechuga Paraíso",
            "price": 2992,
            "type": "mains"
        },
        {
            "name": "Masa de Pescado Frita",
            "price": 2640,
            "type": "mains"
        },
        {
            "name": "Filete de Pescado Grille",
            "price": 2288,
            "type": "mains"
        },
        {
            "name": "Filete John Bill",
            "price": 3256,
            "type": "mains"
        },
        {
            "name": "Camarones a Elección",
            "price": 2995,
            "type": "mains"
        },
        {
            "name": "Pulpo al Gusto",
            "price": 3500,
            "type": "mains"
        },
        {
            "name": "Rueda a las Brasas",
            "price": 3344,
            "type": "mains"
        },
        {
            "name": "Rueda Hemingway",
            "price": 4048,
            "type": "mains"
        },
        {
            "name": "Langosta en Variantes",
            "price": 3168,
            "type": "mains"
        },
        {
            "name": "Langosta Termidor",
            "price": 3520,
            "type": "mains"
        },
        {
            "name": "Caldereta de Mariscos",
            "price": 4480,
            "type": "mains"
        },
        {
            "name": "MonteMari Paraíso",
            "price": 4576,
            "type": "mains"
        },
        {
            "name": "Arroz Frito",
            "price": 2112,
            "type": "mains"
        },
        {
            "name": "Refrito de Garbanzos",
            "price": 1936,
            "type": "mains"
        },
        {
            "name": "Risotto de Pollo y Champiñones",
            "price": 2464,
            "type": "mains"
        },
        {
            "name": "Risotto de Mariscos",
            "price": 3520,
            "type": "mains"
        },
        {
            "name": "Paella",
            "price": 3168,
            "type": "mains"
        },
        {
            "name": "Paella Especial",
            "price": 6600,
            "type": "mains"
        },
        {
            "name": "Pasta Napolitana",
            "price": 1230,
            "type": "pasta"
        },
        {
            "name": "Pasts Amatriciana",
            "price": 1936,
            "type": "pasta"
        },
        {
            "name": "Carbonara",
            "price": 2200,
            "type": "pasta"
        },
        {
            "name": "Nero di Sepia",
            "price": 3256,
            "type": "pasta"
        },
        {
            "name": "Pasta al Pesto",
            "price": 2756,
            "type": "pasta"
        },
        {
            "name": "Lasaña",
            "price": 1895,
            "type": "pasta"
        },
        {
            "name": "Napolitana",
            "price": 1144,
            "type": "pizza"
        },
        {
            "name": "Margarita",
            "price": 1232,
            "type": "pizza"
        },
        {
            "name": "De Cebolla",
            "price": 1325,
            "type": "pizza"
        },
        {
            "name": "Ortolana",
            "price": 1496,
            "type": "pizza"
        },
        {
            "name": "Hawaiana",
            "price": 2288,
            "type": "pizza"
        },
        {
            "name": "Jamón o Chorizo",
            "price": 1760,
            "type": "pizza"
        },
        {
            "name": "De Atún",
            "price": 2640,
            "type": "pizza"
        },
        {
            "name": "De Camarones",
            "price": 2640,
            "type": "pizza"
        },
        {
            "name": "De Jamón Serrano",
            "price": 2816,
            "type": "pizza"
        },
        {
            "name": "Pizza Nel Paraíso",
            "price": 2992,
            "type": "pizza"
        },
        {
            "name": "Arroz Blanco",
            "price": 422,
            "type": "sides"
        },
        {
            "name": "Arroz Moro",
            "price": 636,
            "type": "sides"
        },
        {
            "name": "Arroz Pilaf",
            "price": 880,
            "type": "sides"
        },
        {
            "name": "Puré de Malanga",
            "price": 640,
            "type": "sides"
        },
        {
            "name": "Puré de Viandas",
            "price": 528,
            "type": "sides"
        },
        {
            "name": "Viandas Fritas",
            "price": 528,
            "type": "sides"
        },
        {
            "name": "Papas Fritas",
            "price": 1010,
            "type": "sides"
        },
        {
            "name": "Ensalada de Vegetales",
            "price": 633,
            "type": "sides"
        },
        {
            "name": "Vegetales Salteados",
            "price": 675,
            "type": "sides"
        },
        {
            "name": "Piña / Ají Pimiento",
            "price": 330,
            "type": "sides"
        },
        {
            "name": "Tomate / Cebolla",
            "price": 380,
            "type": "sides"
        },
        {
            "name": "Aceitunas / Bacon",
            "price": 480,
            "type": "sides"
        },
        {
            "name": "Chorizo / Jamón",
            "price": 490,
            "type": "sides"
        },
        {
            "name": "Champiñones",
            "price": 730,
            "type": "sides"
        },
        {
            "name": "Gouda / Atún",
            "price": 800,
            "type": "sides"
        },
        {
            "name": "Camarón / Serrano",
            "price": 945,
            "type": "sides"
        },
        {
            "name": "Flan de caramelo",
            "price": 800,
            "type": "desserts"
        },
        {
            "name": "Bola de Helado",
            "price": 200,
            "type": "desserts"
        },
        {
            "name": "Copa de Helado",
            "price": 895,
            "type": "desserts"
        },
        {
            "name": "Tarta del día",
            "price": 980,
            "type": "desserts"
        },
        {
            "name": "Jugos Naturales",
            "price": 270,
            "type": "non_alcoholic_drinks"
        },
        {
            "name": "Batido de Fruta Natural",
            "price": 450,
            "type": "non_alcoholic_drinks"
        },
        {
            "name": "Malteada",
            "price": 675,
            "type": "non_alcoholic_drinks"
        },
        {
            "name": "Batido de Helado",
            "price": 987,
            "type": "non_alcoholic_drinks"
        },
        {
            "name": "Piña Colada Virgen",
            "price": 700,
            "type": "non_alcoholic_drinks"
        },
        {
            "name": "Limonada Frappé",
            "price": 600,
            "type": "non_alcoholic_drinks"
        },
        {
            "name": "Limonada Frescura",
            "price": 675,
            "type": "non_alcoholic_drinks"
        },
        {
            "name": "Expresso",
            "price": 300,
            "type": "infusions"
        },
        {
            "name": "Cortado",
            "price": 375,
            "type": "infusions"
        },
        {
            "name": "Americano",
            "price": 350,
            "type": "infusions"
        },
        {
            "name": "Capuchino",
            "price": 400,
            "type": "infusions"
        },
        {
            "name": "Frappuccino",
            "price": 400,
            "type": "infusions"
        },
        {
            "name": "Bombón",
            "price": 725,
            "type": "infusions"
        },
        {
            "name": "Irish Coffee",
            "price": 750,
            "type": "infusions"
        },
        {
            "name": "Agua Natural",
            "price": 260,
            "type": "water"
        },
        {
            "name": "Agua Tónica / Gaseada",
            "price": 280,
            "type": "water"
        },
        {
            "name": "Agua Tónica MG",
            "price": 600,
            "type": "water"
        },
        {
            "name": "Refresco Nacional",
            "price": 300,
            "type": "non_alcoholic_drinks"
        },
        {
            "name": "Refresco Importado",
            "price": 350,
            "type": "non_alcoholic_drinks"
        },
        {
            "name": "Malta Nacional",
            "price": 380,
            "type": "non_alcoholic_drinks"
        },
        {
            "name": "Malta Importada",
            "price": 350,
            "type": "non_alcoholic_drinks"
        },
        {
            "name": "Jugo de Lata",
            "price": 390,
            "type": "non_alcoholic_drinks"
        },
        {
            "name": "Jugo de Caja",
            "price": 300,
            "type": "non_alcoholic_drinks"
        },
        {
            "name": "Energizante",
            "price": 330,
            "type": "non_alcoholic_drinks"
        },
        {
            "name": "Red Bull",
            "price": 600,
            "type": "non_alcoholic_drinks"
        },
        {
            "name": "Kermato",
            "price": 600,
            "type": "non_alcoholic_drinks"
        },
        {
            "name": "Cerveza Nacional",
            "price": 375,
            "type": "alcoholic_drinks"
        },
        {
            "name": "Cerveza Importada",
            "price": 330,
            "type": "alcoholic_drinks"
        },
        {
            "name": "Corona / Heineken",
            "price": 600,
            "type": "alcoholic_drinks"
        },
        {
            "name": "Copa de Vino Tinto",
            "price": 600,
            "type": "wines"
        },
        {
            "name": "Copa de Vino Blanco",
            "price": 550,
            "type": "wines"
        },
        {
            "name": "Botellas de Vino Blanco",
            "price": 4000,
            "type": "wines"
        },
        {
            "name": "Botellas de Vino Tinto",
            "price": 5000,
            "type": "wines"
        },
        {
            "name": "Sidra",
            "price": 3000,
            "type": "alcoholic_drinks"
        },
        {
            "name": "Freixenet",
            "price": 6000,
            "type": "alcoholic_drinks"
        },
        {
            "name": "Havana Club 3 años",
            "price": 500,
            "type": "alcoholic_drinks"
        },
        {
            "name": "Havana Club Especial",
            "price": 565,
            "type": "alcoholic_drinks"
        },
        {
            "name": "Havana Club Reserva",
            "price": 800,
            "type": "alcoholic_drinks"
        },
        {
            "name": "Havana Club 7 años",
            "price": 600,
            "type": "alcoholic_drinks"
        },
        {
            "name": "Selección de Maestros",
            "price": 1220,
            "type": "alcoholic_drinks"
        },
        {
            "name": "Black Tears",
            "price": 775,
            "type": "alcoholic_drinks"
        },
        {
            "name": "Absolut",
            "price": 850,
            "type": "alcoholic_drinks"
        },
        {
            "name": "Grey Goose",
            "price": 870,
            "type": "alcoholic_drinks"
        },
        {
            "name": "Stolichnaya",
            "price": 450,
            "type": "alcoholic_drinks"
        },
        {
            "name": "Dewars",
            "price": 800,
            "type": "alcoholic_drinks"
        },
        {
            "name": "Oxford",
            "price": 800,
            "type": "alcoholic_drinks"
        },
        {
            "name": "J&B",
            "price": 800,
            "type": "alcoholic_drinks"
        },
        {
            "name": "Clan Campbell",
            "price": 900,
            "type": "alcoholic_drinks"
        },
        {
            "name": "Ballentines",
            "price": 600,
            "type": "alcoholic_drinks"
        },
        {
            "name": "Buchanans",
            "price": 1200,
            "type": "alcoholic_drinks"
        },
        {
            "name": "J.W Red Label",
            "price": 850,
            "type": "alcoholic_drinks"
        },
        {
            "name": "J.W Black Label",
            "price": 1130,
            "type": "alcoholic_drinks"
        },
        {
            "name": "J.W Double Black Label",
            "price": 1230,
            "type": "alcoholic_drinks"
        },
        {
            "name": "Patrón",
            "price": 1400,
            "type": "alcoholic_drinks"
        },
        {
            "name": "Don Julio",
            "price": 925,
            "type": "alcoholic_drinks"
        },
        {
            "name": "Olmeca",
            "price": 850,
            "type": "alcoholic_drinks"
        },
        {
            "name": "Centenario",
            "price": 800,
            "type": "alcoholic_drinks"
        },
        {
            "name": "Rose",
            "price": 830,
            "type": "alcoholic_drinks"
        },
        {
            "name": "Q",
            "price": 900,
            "type": "alcoholic_drinks"
        },
        {
            "name": "Beefeater",
            "price": 900,
            "type": "alcoholic_drinks"
        },
        {
            "name": "Tanqueray",
            "price": 1320,
            "type": "alcoholic_drinks"
        },
        {
            "name": "Campari",
            "price": 800,
            "type": "alcoholic_drinks"
        },
        {
            "name": "Dactari",
            "price": 800,
            "type": "alcoholic_drinks"
        },
        {
            "name": "Filipetti",
            "price": 800,
            "type": "alcoholic_drinks"
        },
        {
            "name": "Cinzano",
            "price": 800,
            "type": "alcoholic_drinks"
        },
        {
            "name": "Martini",
            "price": 800,
            "type": "alcoholic_drinks"
        },
        {
            "name": "Ricard",
            "price": 800,
            "type": "alcoholic_drinks"
        },
        {
            "name": "Triple Sec",
            "price": 800,
            "type": "alcoholic_drinks"
        },
        {
            "name": "Jagermeister",
            "price": 970,
            "type": "alcoholic_drinks"
        },
        {
            "name": "Carolans",
            "price": 800,
            "type": "alcoholic_drinks"
        },
        {
            "name": "Amarula",
            "price": 800,
            "type": "alcoholic_drinks"
        },
        {
            "name": "Baileys",
            "price": 800,
            "type": "alcoholic_drinks"
        },
        {
            "name": "Amaretto",
            "price": 800,
            "type": "alcoholic_drinks"
        },
        {
            "name": "Cóctel Paraíso",
            "price": 870,
            "type": "cocktails"
        },
        {
            "name": "Manhattan",
            "price": 720,
            "type": "cocktails"
        },
        {
            "name": "Daiikiri",
            "price": 635,
            "type": "cocktails"
        },
        {
            "name": "Cubata",
            "price": 746,
            "type": "cocktails"
        },
        {
            "name": "Cuba Libre",
            "price": 599,
            "type": "cocktails"
        },
        {
            "name": "Cubanito",
            "price": 645,
            "type": "cocktails"
        },
        {
            "name": "Ron Collins",
            "price": 655,
            "type": "cocktails"
        },
        {
            "name": "Blody Mary",
            "price": 825,
            "type": "cocktails"
        },
        {
            "name": "Tinto de Verano",
            "price": 775,
            "type": "cocktails"
        },
        {
            "name": "Sangría",
            "price": 765,
            "type": "cocktails"
        },
        {
            "name": "Mojito",
            "price": 724,
            "type": "cocktails"
        },
        {
            "name": "Tom Collins",
            "price": 950,
            "type": "cocktails"
        },
        {
            "name": "Long Island",
            "price": 1275,
            "type": "cocktails"
        },
        {
            "name": "Michelada",
            "price": 885,
            "type": "cocktails"
        },
        {
            "name": "Michelada Corona",
            "price": 940,
            "type": "cocktails"
        },
        {
            "name": "Michelada Heineken",
            "price": 950,
            "type": "cocktails"
        },
        {
            "name": "Chelada",
            "price": 775,
            "type": "cocktails"
        },
        {
            "name": "Chelada Corona",
            "price": 830,
            "type": "cocktails"
        },
        {
            "name": "Chelada Heineken",
            "price": 850,
            "type": "cocktails"
        },
        {
            "name": "Pina Colada",
            "price": 935,
            "type": "cocktails"
        },
        {
            "name": "Cairoska",
            "price": 785,
            "type": "cocktails"
        },
        {
            "name": "Caipirinha",
            "price": 725,
            "type": "cocktails"
        },
        {
            "name": "Caipiríssima",
            "price": 730,
            "type": "cocktails"
        },
        {
            "name": "Gin Tonic",
            "price": 987,
            "type": "cocktails"
        },
        {
            "name": "Vodka Tonic",
            "price": 795,
            "type": "cocktails"
        },
        {
            "name": "Coctel Martini",
            "price": 950,
            "type": "cocktails"
        },
        {
            "name": "Sreewdriver",
            "price": 825,
            "type": "cocktails"
        },
        {
            "name": "Orgasmo",
            "price": 1216,
            "type": "cocktails"
        },
        {
            "name": "Margarita",
            "price": 825,
            "type": "cocktails"
        }
    ],
    "location": {
        "street": "Acosta #303 esquina Armas",
        "council": null,
        "municipe": "Diez de Octubre",
        "province": "La Habana",
        "zip": null,
        "country": "Cuba",
        "coords_x": null,
        "coords_y": null
    }
}